arable/__init__.py
arable/client.py
arable-0.2.dev4.dist-info/DESCRIPTION.rst
arable-0.2.dev4.dist-info/METADATA
arable-0.2.dev4.dist-info/RECORD
arable-0.2.dev4.dist-info/WHEEL
arable-0.2.dev4.dist-info/metadata.json
arable-0.2.dev4.dist-info/top_level.txt
